datasette_edit_schema/__init__.py
datasette_edit_schema/utils.py
datasette_edit_schema/static/draggable.1.0.0-beta.11.bundle.js
datasette_edit_schema/static/draggable.1.0.0-beta.11.bundle.min.js
datasette_edit_schema/templates/edit_schema_create_table.html
datasette_edit_schema/templates/edit_schema_database.html
datasette_edit_schema/templates/edit_schema_index.html
datasette_edit_schema/templates/edit_schema_table.html
datasette_edit_schema-0.7.1.dist-info/LICENSE
datasette_edit_schema-0.7.1.dist-info/METADATA
datasette_edit_schema-0.7.1.dist-info/WHEEL
datasette_edit_schema-0.7.1.dist-info/entry_points.txt
datasette_edit_schema-0.7.1.dist-info/top_level.txt
datasette_edit_schema-0.7.1.dist-info/RECORD
