Metadata-Version: 2.1
Name: datasette-edit-schema
Version: 0.7.1
Summary: Datasette plugin for modifying table schemas
Home-page: https://github.com/simonw/datasette-edit-schema
Author: Simon Willison
License: Apache License, Version 2.0
Requires-Python: >=3.7
License-File: LICENSE
Requires-Dist: datasette >=0.63
Requires-Dist: sqlite-utils >=3.35
Provides-Extra: test
Requires-Dist: pytest ; extra == 'test'
Requires-Dist: pytest-asyncio ; extra == 'test'
Requires-Dist: beautifulsoup4 ; extra == 'test'
Requires-Dist: html5lib ; extra == 'test'
